yt_dls/__init__.py
yt_dls/main.py
yt_dls-0.0.2.dist-info/LICENSE
yt_dls-0.0.2.dist-info/METADATA
yt_dls-0.0.2.dist-info/WHEEL
yt_dls-0.0.2.dist-info/entry_points.txt
yt_dls-0.0.2.dist-info/top_level.txt
yt_dls-0.0.2.dist-info/RECORD
