Metadata-Version: 2.1
Name: yt-dls
Version: 0.0.2
Summary: Download videos from YouTube
License: MIT License
License-File: LICENSE
Requires-Dist: colorlog
Requires-Dist: yt-dlp
